MANIFEST.in
README.txt
setup.cfg
setup.py
stylons/__init__.py
stylons/websetup.py
stylons.egg-info/PKG-INFO
stylons.egg-info/SOURCES.txt
stylons.egg-info/dependency_links.txt
stylons.egg-info/entry_points.txt
stylons.egg-info/not-zip-safe
stylons.egg-info/paster_plugins.txt
stylons.egg-info/requires.txt
stylons.egg-info/top_level.txt
stylons/config/__init__.py
stylons/config/deployment.ini_tmpl
stylons/config/environment.py
stylons/config/hashid.py
stylons/config/middleware.py
stylons/config/routing.py
stylons/controllers/__init__.py
stylons/controllers/buttons.py
stylons/controllers/error.py
stylons/controllers/forms.py
stylons/controllers/list.py
stylons/controllers/main.py
stylons/controllers/showtime.py
stylons/controllers/stylons_.py
stylons/controllers/testowy.py
stylons/controllers/timer.py
stylons/lib/__init__.py
stylons/lib/app_globals.py
stylons/lib/base.py
stylons/lib/helpers.py
stylons/model/__init__.py
stylons/model/meta.py
stylons/public/index.html
stylons/public/oldindex.html
stylons/public/orders.html
stylons/public/style.css
stylons/public/lib/sencha/index.html
stylons/public/lib/sencha/license.inc
stylons/public/lib/sencha/license.txt
stylons/public/lib/sencha/release-notes.html
stylons/public/lib/sencha/sencha-touch-debug-w-comments.js
stylons/public/lib/sencha/sencha-touch-debug.js
stylons/public/lib/sencha/sencha-touch.js
stylons/public/lib/sencha/sencha-touch.jsb3
stylons/public/lib/sencha/resources/css/android.css
stylons/public/lib/sencha/resources/css/apple.css
stylons/public/lib/sencha/resources/css/bb6.css
stylons/public/lib/sencha/resources/css/sencha-touch.css
stylons/public/lib/sencha/resources/css-debug/android.css
stylons/public/lib/sencha/resources/css-debug/apple.css
stylons/public/lib/sencha/resources/css-debug/bb6.css
stylons/public/lib/sencha/resources/css-debug/sencha-touch.css
stylons/public/lib/sencha/resources/sass/android.scss
stylons/public/lib/sencha/resources/sass/apple.scss
stylons/public/lib/sencha/resources/sass/bb6.scss
stylons/public/lib/sencha/resources/sass/config-debug.rb
stylons/public/lib/sencha/resources/sass/config-release.rb
stylons/public/lib/sencha/resources/sass/config.rb
stylons/public/lib/sencha/resources/sass/sencha-touch.scss
