Metadata-Version: 1.0
Name: stylons
Version: 1.0dev
Summary: Stylons is Python + Sencha Touch framework for mobile apps. 
Home-page: http://stylons.org
Author: Stylons Team
Author-email: marcin.kliks@gmail.com
License: UNKNOWN
Platform: UNKNOWN
